EBRPIH1118_intf/__init__.py
EBRPIH1118_intf/ebrpih1118.py
EBRPIH1118-0.1.4.dist-info/LICENSE
EBRPIH1118-0.1.4.dist-info/METADATA
EBRPIH1118-0.1.4.dist-info/WHEEL
EBRPIH1118-0.1.4.dist-info/top_level.txt
EBRPIH1118-0.1.4.dist-info/RECORD
