Metadata-Version: 2.1
Name: EBRPIH1118
Version: 0.1.4
Summary: A Python package to interface with the board, and control relays, digital inputs/outputs, and analog inputs on Raspberry Pi.
Home-page: https://www.electronbits.com
Author: ElectronBits
Author-email: info@electronbits.com
Project-URL: Website, https://www.electronbits.com
Project-URL: Source, https://github.com/electronbits/Py_EBRPIH1118
Classifier: Programming Language :: Python :: 3
Classifier: License :: OSI Approved :: MIT License
Classifier: Operating System :: OS Independent
Requires-Python: >=3.6
License-File: LICENSE
Requires-Dist: RPi.GPIO
Requires-Dist: spidev
